predictoor_data/__init__.py
predictoor_data/client.py
predictoor_data/constants.py
predictoor_data/exceptions.py
predictoor_data/pair_data.py
predictoor_data/py.typed
predictoor_data/abis/ERC20Template3.json
predictoor_data/abis/FixedRateExchange.json
predictoor_data/contract/__init__.py
predictoor_data/contract/base_contract.py
predictoor_data/contract/feed_contract.py
predictoor_data/contract/fixed_rate.py
predictoor_data/contract/token.py
predictoor_data/subgraph/__init__.py
predictoor_data/subgraph/contract_address.py
predictoor_data/subgraph/historical_data.py
predictoor_data/subgraph/query.py
predictoor_data/util/__init__.py
predictoor_data/util/currency_types.py
predictoor_data/w3_config/__init__.py
predictoor_data/w3_config/w3_config.py
predictoor_data-0.1.7.dist-info/METADATA
predictoor_data-0.1.7.dist-info/WHEEL
predictoor_data-0.1.7.dist-info/top_level.txt
predictoor_data-0.1.7.dist-info/RECORD
