Metadata-Version: 2.2
Name: predictoor-data
Version: 0.1.7
Summary: A package for fetching historical and prediction data
Home-page: https://github.com/oceanprotocol/predictoor-data
Author: oceanprotocol
Author-email: devops@oceanprotocol.com
Classifier: Development Status :: 2 - Pre-Alpha
Classifier: Intended Audience :: Developers
Classifier: License :: OSI Approved :: Apache Software License
Classifier: Natural Language :: English
Classifier: Programming Language :: Python :: 3
Requires-Python: >=3.7
Requires-Dist: requests>=2.25.0
Requires-Dist: pandas>=1.2.0
Requires-Dist: python-dateutil>=2.8.0
Requires-Dist: pytest>=6.0.0
Requires-Dist: mypy>=0.900
Requires-Dist: black>=21.0
Requires-Dist: web3==6.20.2
Requires-Dist: eth-account==0.11.0
Dynamic: author
Dynamic: author-email
Dynamic: classifier
Dynamic: description
Dynamic: description-content-type
Dynamic: home-page
Dynamic: requires-dist
Dynamic: requires-python
Dynamic: summary
